pytesimal/__init__.py
pytesimal/analysis.py
pytesimal/core_function.py
pytesimal/load_plot_save.py
pytesimal/mantle_properties.py
pytesimal/numerical_methods.py
pytesimal/quick_workflow.py
pytesimal/setup_functions.py
pytesimal-2.0.0.dist-info/LICENSE
pytesimal-2.0.0.dist-info/METADATA
pytesimal-2.0.0.dist-info/WHEEL
pytesimal-2.0.0.dist-info/top_level.txt
pytesimal-2.0.0.dist-info/RECORD
