Metadata-Version: 2.1
Name: pytesimal
Version: 2.0.0
Summary: Model the conductive cooling of planetesimals with temperature-dependent material properties.
Home-page: https://github.com/murphyqm/pytesimal
Author: M. Murphy Quinlan, A.M. Walker, P. Selves, L.S.E. Teggin
Author-email: eememq@leeds.ac.uk
License: UNKNOWN
Project-URL: Documentation, https://pytesimal.readthedocs.io/en/latest/
Project-URL: Bug Tracker, https://github.com/pypa/sampleproject/issues
Project-URL: Scientific Background:, https://doi.org/10.1029/2020JE006726
Platform: UNKNOWN
Classifier: Programming Language :: Python
Classifier: License :: OSI Approved :: MIT License
Classifier: Operating System :: OS Independent
Classifier: Topic :: Scientific/Engineering
Classifier: Intended Audience :: Science/Research
Classifier: Natural Language :: English
Requires-Python: >=3.7
Requires-Dist: numpy
Requires-Dist: matplotlib
